pennylane_kq/__init__.py
pennylane_kq/_version.py
pennylane_kq/kq_device.py
pennylane_kq/kq_emulator.py
pennylane_kq/kq_emulator_aws.py
pennylane_kq/kq_emulator_mpi.py
pennylane_kq/kq_fast_emulator.py
pennylane_kq/kq_hardware.py
pennylane_kq/kq_local_emulator.py
pennylane_kq/kq_remote_emulator.py
pennylane_kq-0.0.31.dist-info/LICENSE
pennylane_kq-0.0.31.dist-info/METADATA
pennylane_kq-0.0.31.dist-info/WHEEL
pennylane_kq-0.0.31.dist-info/entry_points.txt
pennylane_kq-0.0.31.dist-info/top_level.txt
pennylane_kq-0.0.31.dist-info/RECORD
